{
  "mode": "daily",
  "date": "2026-04-27",
  "totals": {
    "totalUsers": "114",
    "newUsers": "91",
    "sessions": "140",
    "screenPageViews": "252",
    "engagementRate": "0.54285714285714282",
    "bounceRate": "0.45714285714285713"
  },
  "by_channel": [
    {
      "sessionDefaultChannelGroup": "Direct",
      "totalUsers": "69",
      "sessions": "83",
      "engagementRate": "0.43373493975903615"
    },
    {
      "sessionDefaultChannelGroup": "Organic Search",
      "totalUsers": "36",
      "sessions": "44",
      "engagementRate": "0.68181818181818177"
    },
    {
      "sessionDefaultChannelGroup": "Referral",
      "totalUsers": "6",
      "sessions": "8",
      "engagementRate": "0.875"
    },
    {
      "sessionDefaultChannelGroup": "Email",
      "totalUsers": "3",
      "sessions": "4",
      "engagementRate": "0.5"
    },
    {
      "sessionDefaultChannelGroup": "Paid Search",
      "totalUsers": "1",
      "sessions": "1",
      "engagementRate": "1"
    }
  ],
  "by_source": [
    {
      "sessionSource": "(direct)",
      "sessionMedium": "(none)",
      "totalUsers": "69",
      "sessions": "83"
    },
    {
      "sessionSource": "google",
      "sessionMedium": "organic",
      "totalUsers": "19",
      "sessions": "22"
    },
    {
      "sessionSource": "bing",
      "sessionMedium": "organic",
      "totalUsers": "14",
      "sessions": "19"
    },
    {
      "sessionSource": "hs_email",
      "sessionMedium": "email",
      "totalUsers": "3",
      "sessions": "4"
    },
    {
      "sessionSource": "heartlanddental.sharepoint.com",
      "sessionMedium": "referral",
      "totalUsers": "2",
      "sessions": "2"
    },
    {
      "sessionSource": "yahoo",
      "sessionMedium": "organic",
      "totalUsers": "2",
      "sessions": "2"
    },
    {
      "sessionSource": "apollo.vitalcare.com",
      "sessionMedium": "referral",
      "totalUsers": "1",
      "sessions": "1"
    },
    {
      "sessionSource": "duckduckgo",
      "sessionMedium": "organic",
      "totalUsers": "1",
      "sessions": "1"
    },
    {
      "sessionSource": "google",
      "sessionMedium": "cpc",
      "totalUsers": "1",
      "sessions": "1"
    },
    {
      "sessionSource": "mail.google.com",
      "sessionMedium": "referral",
      "totalUsers": "1",
      "sessions": "3"
    },
    {
      "sessionSource": "ppscconfluence:8090",
      "sessionMedium": "referral",
      "totalUsers": "1",
      "sessions": "1"
    },
    {
      "sessionSource": "statics.teams.cdn.office.net",
      "sessionMedium": "referral",
      "totalUsers": "1",
      "sessions": "1"
    }
  ],
  "top_pages": [
    {
      "pagePath": "/state-exclusion-databases-medicaid-exclusion/",
      "screenPageViews": "65",
      "totalUsers": "40"
    },
    {
      "pagePath": "/",
      "screenPageViews": "35",
      "totalUsers": "28"
    },
    {
      "pagePath": "/systems-login/",
      "screenPageViews": "18",
      "totalUsers": "6"
    },
    {
      "pagePath": "/north-carolina-medicaid-exclusion-list/",
      "screenPageViews": "10",
      "totalUsers": "6"
    },
    {
      "pagePath": "/florida-medicaid-exclusion-list/",
      "screenPageViews": "8",
      "totalUsers": "3"
    },
    {
      "pagePath": "/providers-guide-to-oig-exclusions/",
      "screenPageViews": "6",
      "totalUsers": "6"
    },
    {
      "pagePath": "/onboarding-safer-plus/",
      "screenPageViews": "5",
      "totalUsers": "5"
    },
    {
      "pagePath": "/pennsylvania-medicaid-exclusion-list/",
      "screenPageViews": "5",
      "totalUsers": "4"
    },
    {
      "pagePath": "/compliance-hotline/",
      "screenPageViews": "4",
      "totalUsers": "4"
    },
    {
      "pagePath": "/new-jersey-medicaid-exclusion-list/",
      "screenPageViews": "4",
      "totalUsers": "3"
    },
    {
      "pagePath": "/state-medicaid-exclusion-lists/",
      "screenPageViews": "4",
      "totalUsers": "4"
    },
    {
      "pagePath": "/tennessee-medicaid-exclusion-list/",
      "screenPageViews": "4",
      "totalUsers": "3"
    },
    {
      "pagePath": "/alaska-medicaid-exclusion-list/",
      "screenPageViews": "3",
      "totalUsers": "1"
    },
    {
      "pagePath": "/exclusion-screening/",
      "screenPageViews": "3",
      "totalUsers": "3"
    },
    {
      "pagePath": "/how-it-works/",
      "screenPageViews": "3",
      "totalUsers": "2"
    },
    {
      "pagePath": "/indiana-medicaid-exclusion-list/",
      "screenPageViews": "3",
      "totalUsers": "2"
    },
    {
      "pagePath": "/pricing/",
      "screenPageViews": "3",
      "totalUsers": "3"
    },
    {
      "pagePath": "/request-access/",
      "screenPageViews": "3",
      "totalUsers": "3"
    },
    {
      "pagePath": "/schedule-a-demo/",
      "screenPageViews": "3",
      "totalUsers": "2"
    },
    {
      "pagePath": "/systemlogin/",
      "screenPageViews": "3",
      "totalUsers": "3"
    }
  ],
  "property": {
    "key": "exsc",
    "name": "Exclusion Screening",
    "domain": "exclusionscreening.com",
    "slack_channel": "#marketing-analytics"
  }
}